fiximports/__init__.py
fiximports/fiximports.py
fiximports-0.1.18.data/data/share/fiximports/docs/Makefile
fiximports-0.1.18.data/data/share/fiximports/docs/make.bat
fiximports-0.1.18.data/data/share/fiximports/docs/source/conf.py
fiximports-0.1.18.data/data/share/fiximports/docs/source/index.rst
fiximports-0.1.18.dist-info/DESCRIPTION.rst
fiximports-0.1.18.dist-info/METADATA
fiximports-0.1.18.dist-info/RECORD
fiximports-0.1.18.dist-info/WHEEL
fiximports-0.1.18.dist-info/entry_points.txt
fiximports-0.1.18.dist-info/metadata.json
fiximports-0.1.18.dist-info/pbr.json
fiximports-0.1.18.dist-info/top_level.txt
