Metadata-Version: 2.0
Name: fiximports
Version: 0.1.18
Summary: Reorder import statements in Python files
Home-page: https://github.com/Stibbons/fiximports
Author: Gaetan Semet
Author-email: gaetan@xeberon.net
License: Apache-2
Keywords: codesstyle
Platform: UNKNOWN
Classifier: Development Status :: 4 - Beta
Classifier: Environment :: Console
Classifier: Intended Audience :: Developers
Classifier: Intended Audience :: Information Technology
Classifier: License :: OSI Approved :: Apache Software License
Classifier: Operating System :: OS Independent
Classifier: Programming Language :: Python
Requires-Dist: setuptools (>=17.1)
Requires-Dist: pip (>=1.0)
Requires-Dist: six (>=1.10.0)
Requires-Dist: argparse; (python_version=='2.6')
